switcore/__init__.py
switcore/constants.py
switcore/logger.py
switcore/lokalise.py
switcore/type.py
switcore/action/__init__.py
switcore/action/activity_handler_abc.py
switcore/action/activity_router.py
switcore/action/dependencies.py
switcore/action/exceptions.py
switcore/action/schemas.py
switcore/auth/__init__.py
switcore/auth/constants.py
switcore/auth/dependencies.py
switcore/auth/exception.py
switcore/auth/models.py
switcore/auth/oauth2.py
switcore/auth/repository.py
switcore/auth/router.py
switcore/auth/schemas.py
switcore/auth/signature_verification.py
switcore/auth/utils.py
switcore/ui/Icon.py
switcore/ui/__init__.py
switcore/ui/button.py
switcore/ui/collection_entry.py
switcore/ui/container.py
switcore/ui/divider.py
switcore/ui/file.py
switcore/ui/header.py
switcore/ui/html_frame.py
switcore/ui/image.py
switcore/ui/input.py
switcore/ui/select.py
switcore/ui/select_item.py
switcore/ui/signIn_page.py
switcore/ui/static_action.py
switcore/ui/tabs.py
switcore/ui/text_paragraph.py
switcore/ui/textarea.py
switbuilder_core-0.0.17.dist-info/METADATA
switbuilder_core-0.0.17.dist-info/WHEEL
switbuilder_core-0.0.17.dist-info/RECORD
