Metadata-Version: 2.1
Name: switbuilder-core
Version: 0.0.17
Summary: this is a switbuilder core package
Project-URL: Homepage, https://github.com/pypa/sampleproject
Project-URL: Bug Tracker, https://github.com/pypa/sampleproject/issues
Author-email: ur-team <el.lee@swit.io>
Classifier: License :: OSI Approved :: MIT License
Classifier: Operating System :: OS Independent
Classifier: Programming Language :: Python :: 3
Requires-Python: >=3.10
Requires-Dist: fastapi>=0.83.0
Requires-Dist: httpx-oauth>=0.11.2
Requires-Dist: httpx>=0.24.1
Requires-Dist: pydantic>=1.10.9
Requires-Dist: pymysql>=1.1.0
Requires-Dist: sqlalchemy>=1.4.41
